pyxll/__init__.py
pyxll/_cli.py
pyxll/_utils.py
pyxll/_errors.py
pyxll/_check.py
pyxll/_install.py
pyxll/_update.py
pyxll/_activate.py
pyxll/_config.py
pyxll/_uninstall.py
pyxll/_cert.py
pyxll/_admin.py
pyxll/__main__.py
pyxll/pyxll.crt
pyxll/py.typed
pyxll-5.11.2.dist-info/entry_points.txt
pyxll-5.11.2.dist-info/DESCRIPTION.rst
pyxll-5.11.2.dist-info/METADATA
pyxll-5.11.2.dist-info/metadata.json
pyxll-5.11.2.dist-info/top_level.txt
pyxll-5.11.2.dist-info/WHEEL
pyxll-5.11.2.dist-info/RECORD