Metadata-Version: 2.1
Name: pyxll
Version: 5.11.2
Summary: Write Microsoft Excel Add-Ins in Python
Home-page: https://www.pyxll.com
Author: PyXLL Ltd
Author-email: info@pyxll.com
License: Other/Proprietary License
Platform: Windows
Classifier: Development Status :: 6 - Mature
Classifier: Environment :: Win32 (MS Windows)
Classifier: License :: Other/Proprietary License
Classifier: Natural Language :: English
Classifier: Operating System :: Microsoft :: Windows
Classifier: Programming Language :: Python
Classifier: Programming Language :: Python :: 2
Classifier: Programming Language :: Python :: 3
Classifier: Topic :: Office/Business :: Office Suites
